CHANGELOG.md
sgzenity/__init__.py
sgzenity/sgszenity.py
sgzenity-1.0.4.dist-info/LICENSE
sgzenity-1.0.4.dist-info/METADATA
sgzenity-1.0.4.dist-info/WHEEL
sgzenity-1.0.4.dist-info/entry_points.txt
sgzenity-1.0.4.dist-info/RECORD
