Metadata-Version: 2.1
Name: sgzenity
Version: 1.0.4
Summary: sgzentry is a library for python which was inspired by Zenity. When you write scripts, you can use sgzentry to create simple dialogs that interact graphically with the user.
Home-page: https://github.com/SoftGeekRO/sgzenity
License: GPL-3.0-or-later
Keywords: zenity,python3,poetry,dialog,GTK+3
Author: Zaharia Constantin
Author-email: constantin.zaharia@sgsolar.ro
Requires-Python: >=3.10,<4.0
Classifier: License :: OSI Approved :: GNU General Public License v3 or later (GPLv3+)
Classifier: License :: OSI Approved :: GNU Lesser General Public License v3 (LGPLv3)
Classifier: Operating System :: OS Independent
Classifier: Programming Language :: Python
Classifier: Programming Language :: Python :: 3
Classifier: Programming Language :: Python :: 3.10
Classifier: Programming Language :: Python :: 3.11
Classifier: Programming Language :: Python :: 3.12
Classifier: Programming Language :: Python :: 3.13
Classifier: Programming Language :: Python :: 3.14
Classifier: Topic :: Software Development :: Libraries
Classifier: Topic :: Software Development :: Libraries :: Python Modules
Project-URL: Documentation, https://soulraven.github.io/roundbox/
Project-URL: Discussions, https://github.com/soulraven/roundbox/discussions
Project-URL: Issues, https://github.com/soulraven/roundbox/issues
Project-URL: Repository, https://github.com/SoftGeekRO/sgzenity.git
Project-URL: Releases, https://soulraven.github.io/roundbox/releases
Project-URL: Source, https://github.com/soulraven/roundbox
